{
  "readme": {
    "name": "readme",
    "type": "file",
    "content": ["This is a readme"]
  },
  "anotherfile": {
    "name": "anotherfile",
    "type": "file",
    "content": ["This is another file"]
  },
  "help": {
    "name": "help",
    "type": "file",
    "content": [
      "Commands:\n",
      " dir - Shows the current directory content\n",
      " open <file-name> - Opens the file\n",
      " This is very simple!"
    ]
  },
  "venti": {
    "name": "venti",
    "type": "image"
  }
}
